mcp_gsuite/__init__.py
mcp_gsuite/calendar.py
mcp_gsuite/gauth.py
mcp_gsuite/gmail.py
mcp_gsuite/server.py
mcp_gsuite/toolhandler.py
mcp_gsuite/tools_calendar.py
mcp_gsuite/tools_gmail.py
mseep_mcp_gsuite_enhanced-2.0.1.dist-info/METADATA
mseep_mcp_gsuite_enhanced-2.0.1.dist-info/WHEEL
mseep_mcp_gsuite_enhanced-2.0.1.dist-info/entry_points.txt
mseep_mcp_gsuite_enhanced-2.0.1.dist-info/licenses/LICENSE
mseep_mcp_gsuite_enhanced-2.0.1.dist-info/RECORD
